[
  {
    "login": "hojberg",
    "id": 2371,
    "node_id": "MDQ6VXNlcjIzNzE=",
    "avatar_url": "https://avatars.githubusercontent.com/u/2371?v=4",
    "gravatar_id": "",
    "url": "https://api.github.com/users/hojberg",
    "html_url": "https://github.com/hojberg",
    "followers_url": "https://api.github.com/users/hojberg/followers",
    "following_url": "https://api.github.com/users/hojberg/following{/other_user}",
    "gists_url": "https://api.github.com/users/hojberg/gists{/gist_id}",
    "starred_url": "https://api.github.com/users/hojberg/starred{/owner}{/repo}",
    "subscriptions_url": "https://api.github.com/users/hojberg/subscriptions",
    "organizations_url": "https://api.github.com/users/hojberg/orgs",
    "repos_url": "https://api.github.com/users/hojberg/repos",
    "events_url": "https://api.github.com/users/hojberg/events{/privacy}",
    "received_events_url": "https://api.github.com/users/hojberg/received_events",
    "type": "User",
    "site_admin": false,
    "contributions": 2
  },
  {
    "login": "sophiebits-humu",
    "id": 46688646,
    "node_id": "MDQ6VXNlcjQ2Njg4NjQ2",
    "avatar_url": "https://avatars.githubusercontent.com/u/46688646?v=4",
    "gravatar_id": "",
    "url": "https://api.github.com/users/sophiebits-humu",
    "html_url": "https://github.com/sophiebits-humu",
    "followers_url": "https://api.github.com/users/sophiebits-humu/followers",
    "following_url": "https://api.github.com/users/sophiebits-humu/following{/other_user}",
    "gists_url": "https://api.github.com/users/sophiebits-humu/gists{/gist_id}",
    "starred_url": "https://api.github.com/users/sophiebits-humu/starred{/owner}{/repo}",
    "subscriptions_url": "https://api.github.com/users/sophiebits-humu/subscriptions",
    "organizations_url": "https://api.github.com/users/sophiebits-humu/orgs",
    "repos_url": "https://api.github.com/users/sophiebits-humu/repos",
    "events_url": "https://api.github.com/users/sophiebits-humu/events{/privacy}",
    "received_events_url": "https://api.github.com/users/sophiebits-humu/received_events",
    "type": "User",
    "site_admin": false,
    "contributions": 2
  },
  {
    "login": "stkb",
    "id": 6125444,
    "node_id": "MDQ6VXNlcjYxMjU0NDQ=",
    "avatar_url": "https://avatars.githubusercontent.com/u/6125444?v=4",
    "gravatar_id": "",
    "url": "https://api.github.com/users/stkb",
    "html_url": "https://github.com/stkb",
    "followers_url": "https://api.github.com/users/stkb/followers",
    "following_url": "https://api.github.com/users/stkb/following{/other_user}",
    "gists_url": "https://api.github.com/users/stkb/gists{/gist_id}",
    "starred_url": "https://api.github.com/users/stkb/starred{/owner}{/repo}",
    "subscriptions_url": "https://api.github.com/users/stkb/subscriptions",
    "organizations_url": "https://api.github.com/users/stkb/orgs",
    "repos_url": "https://api.github.com/users/stkb/repos",
    "events_url": "https://api.github.com/users/stkb/events{/privacy}",
    "received_events_url": "https://api.github.com/users/stkb/received_events",
    "type": "User",
    "site_admin": false,
    "contributions": 2
  },
  {
    "login": "stoyan",
    "id": 51308,
    "node_id": "MDQ6VXNlcjUxMzA4",
    "avatar_url": "https://avatars.githubusercontent.com/u/51308?v=4",
    "gravatar_id": "",
    "url": "https://api.github.com/users/stoyan",
    "html_url": "https://github.com/stoyan",
    "followers_url": "https://api.github.com/users/stoyan/followers",
    "following_url": "https://api.github.com/users/stoyan/following{/other_user}",
    "gists_url": "https://api.github.com/users/stoyan/gists{/gist_id}",
    "starred_url": "https://api.github.com/users/stoyan/starred{/owner}{/repo}",
    "subscriptions_url": "https://api.github.com/users/stoyan/subscriptions",
    "organizations_url": "https://api.github.com/users/stoyan/orgs",
    "repos_url": "https://api.github.com/users/stoyan/repos",
    "events_url": "https://api.github.com/users/stoyan/events{/privacy}",
    "received_events_url": "https://api.github.com/users/stoyan/received_events",
    "type": "User",
    "site_admin": false,
    "contributions": 2
  },
  {
    "login": "fforw",
    "id": 226774,
    "node_id": "MDQ6VXNlcjIyNjc3NA==",
    "avatar_url": "https://avatars.githubusercontent.com/u/226774?v=4",
    "gravatar_id": "",
    "url": "https://api.github.com/users/fforw",
    "html_url": "https://github.com/fforw",
    "followers_url": "https://api.github.com/users/fforw/followers",
    "following_url": "https://api.github.com/users/fforw/following{/other_user}",
    "gists_url": "https://api.github.com/users/fforw/gists{/gist_id}",
    "starred_url": "https://api.github.com/users/fforw/starred{/owner}{/repo}",
    "subscriptions_url": "https://api.github.com/users/fforw/subscriptions",
    "organizations_url": "https://api.github.com/users/fforw/orgs",
    "repos_url": "https://api.github.com/users/fforw/repos",
    "events_url": "https://api.github.com/users/fforw/events{/privacy}",
    "received_events_url": "https://api.github.com/users/fforw/received_events",
    "type": "User",
    "site_admin": false,
    "contributions": 2
  },
  {
    "login": "sverrejoh",
    "id": 1209,
    "node_id": "MDQ6VXNlcjEyMDk=",
    "avatar_url": "https://avatars.githubusercontent.com/u/1209?v=4",
    "gravatar_id": "",
    "url": "https://api.github.com/users/sverrejoh",
    "html_url": "https://github.com/sverrejoh",
    "followers_url": "https://api.github.com/users/sverrejoh/followers",
    "following_url": "https://api.github.com/users/sverrejoh/following{/other_user}",
    "gists_url": "https://api.github.com/users/sverrejoh/gists{/gist_id}",
    "starred_url": "https://api.github.com/users/sverrejoh/starred{/owner}{/repo}",
    "subscriptions_url": "https://api.github.com/users/sverrejoh/subscriptions",
    "organizations_url": "https://api.github.com/users/sverrejoh/orgs",
    "repos_url": "https://api.github.com/users/sverrejoh/repos",
    "events_url": "https://api.github.com/users/sverrejoh/events{/privacy}",
    "received_events_url": "https://api.github.com/users/sverrejoh/received_events",
    "type": "User",
    "site_admin": false,
    "contributions": 2
  }
]